trinityml/__init__.py
trinityml/preprod_tracing.py
trinityml-0.0.18.dist-info/METADATA
trinityml-0.0.18.dist-info/WHEEL
trinityml-0.0.18.dist-info/top_level.txt
trinityml-0.0.18.dist-info/RECORD
