Metadata-Version: 2.4
Name: trinityml
Version: 0.0.18
Summary: A Python SDK for recording the LLM Experiment Execution
Home-page: https://github.com/roosterhr/gg_python_sdk
Author: Team Trinity
Author-email: support@giggso.com
Classifier: Programming Language :: Python :: 3
Classifier: License :: OSI Approved :: MIT License
Classifier: Operating System :: OS Independent
Requires-Dist: langfuse==2.60.7
Requires-Dist: httpx
Dynamic: author
Dynamic: author-email
Dynamic: classifier
Dynamic: description
Dynamic: description-content-type
Dynamic: home-page
Dynamic: requires-dist
Dynamic: summary
